DS_Store_Cleaner/DS_Store_Cleaner.py
DS_Store_Cleaner/__init__.py
DS_Store_Cleaner/__main__.py
DS_Store_Cleaner-0.2.dist-info/LICENSE
DS_Store_Cleaner-0.2.dist-info/METADATA
DS_Store_Cleaner-0.2.dist-info/WHEEL
DS_Store_Cleaner-0.2.dist-info/entry_points.txt
DS_Store_Cleaner-0.2.dist-info/top_level.txt
DS_Store_Cleaner-0.2.dist-info/RECORD
